markshark/__init__.py
markshark/_version.py
markshark/align_core.py
markshark/app_streamlit.py
markshark/cli.py
markshark/defaults.py
markshark/gui_launcher.py
markshark/mapviewer_core.py
markshark/mock_dataset.py
markshark/project_utils.py
markshark/score_core.py
markshark/template_manager.py
markshark/user_preferences.py
markshark/assets/banner.png
markshark/assets/markshark-fonts.css
markshark/assets/fonts/OFL.txt
markshark/assets/fonts/Poppins-Bold.ttf
markshark/assets/fonts/Poppins-BoldItalic.ttf
markshark/assets/fonts/Poppins-Italic.ttf
markshark/assets/fonts/Poppins-Regular.ttf
markshark/assets/fonts/Poppins-SemiBold.ttf
markshark/assets/fonts/Poppins-SemiBoldItalic.ttf
markshark/assets/sample_data/README.txt
markshark/assets/sample_data/mock_answer_key.txt
markshark/assets/sample_data/mock_scans.pdf
markshark/assets/sample_data/mock_student_responses.csv
markshark/templates/MarkShark-232Q/bubblemap.yaml
markshark/templates/MarkShark-232Q/master_template.pdf
markshark/templates/MarkShark-64Q/bubblemap.yaml
markshark/templates/MarkShark-64Q/master_template.pdf
markshark/templates/archived/MarkShark-80Q/bubblemap.yaml
markshark/templates/archived/MarkShark-80Q/master_template.pdf
markshark/templates/archived/UofT-med-220Q/bubblemap.yaml
markshark/templates/archived/UofT-med-220Q/master_template.pdf
markshark/templates/archived/UofT-med-48Q copy/bubblemap.yaml
markshark/templates/archived/UofT-med-48Q copy/master_template.pdf
markshark/tools/__init__.py
markshark/tools/align_tools.py
markshark/tools/bubblemap_io.py
markshark/tools/io_pages.py
markshark/tools/report_tools.py
markshark/tools/score_tools.py
markshark/tools/stats_tools.py
markshark/tools/visualizer_tools.py
markshark-1.0.2.dist-info/METADATA
markshark-1.0.2.dist-info/WHEEL
markshark-1.0.2.dist-info/entry_points.txt
markshark-1.0.2.dist-info/licenses/LICENSE
markshark-1.0.2.dist-info/licenses/NOTICE.txt
markshark-1.0.2.dist-info/RECORD
