Metadata-Version: 2.4
Name: markshark
Version: 1.0.2
Summary: MarkShark — the open-source bubble hunter (Optical Mark Recognition toolkit)
Project-URL: Homepage, https://github.com/navarrew/markshark
Project-URL: Repository, https://github.com/navarrew/markshark
Project-URL: Issues, https://github.com/navarrew/markshark/issues
Author-email: William Navarre <william.navarre@utoronto.ca>
License: AGPL-3.0-only with dual commercial licensing available; contact william.navarre@utoronto.ca
License-File: LICENSE
License-File: NOTICE.txt
Classifier: Intended Audience :: Education
Classifier: License :: OSI Approved :: GNU Affero General Public License v3
Classifier: Programming Language :: Python :: 3
Classifier: Programming Language :: Python :: 3.9
Classifier: Programming Language :: Python :: 3.10
Classifier: Programming Language :: Python :: 3.11
Classifier: Programming Language :: Python :: 3.12
Classifier: Topic :: Education
Classifier: Topic :: Scientific/Engineering :: Image Recognition
Requires-Python: >=3.9
Requires-Dist: matplotlib>=3.8
Requires-Dist: numpy<2.0,>=1.26
Requires-Dist: opencv-contrib-python>=4.9
Requires-Dist: openpyxl>=3.0
Requires-Dist: pandas<2.3,>=2.1
Requires-Dist: pdf2image>=1.17
Requires-Dist: pymupdf>=1.24
Requires-Dist: pyyaml
Requires-Dist: rapidfuzz>=3.0
Requires-Dist: rich>=13.7
Requires-Dist: streamlit-antd-components>=0.3.2
Requires-Dist: streamlit>=1.35
Requires-Dist: typer>=0.12
